setup.py
cmigemo/__init__.py
cmigemo/info.py
cmigemo/migemo.py
cmigemo.egg-info/PKG-INFO
cmigemo.egg-info/SOURCES.txt
cmigemo.egg-info/dependency_links.txt
cmigemo.egg-info/requires.txt
cmigemo.egg-info/top_level.txt
test/test_cmigemo.py