Metadata-Version: 1.1
Name: cmigemo
Version: 0.1.5
Summary: A pure python binding for C/Migemo
Home-page: https://github.com/mooz/python-cmigemo
Author: Masafumi Oyamada
Author-email: stillpedant@gmail.com
License: MIT
Keywords: C/Migemo ctypes
Platform: UNKNOWN
Classifier: Operating System :: POSIX
